pixelist/__init__.py
pixelist/engine.py
pixelist/enum.py
pixelist/features.py
pixelist/filter.py
pixelist/image.py
pixelist-0.2.3.dist-info/LICENSE
pixelist-0.2.3.dist-info/METADATA
pixelist-0.2.3.dist-info/WHEEL
pixelist-0.2.3.dist-info/top_level.txt
pixelist-0.2.3.dist-info/RECORD
