Metadata-Version: 2.2
Name: pixelist
Version: 0.2.3
Summary: Experiment with image filter workflows, by superpositions.
Author-email: AARMN The Limitless <aarmn80@gmail.com>
License: MIT
Project-URL: Homepage, https://github.com/aarmn/pixelist
Project-URL: Repository, https://github.com/aarmn/pixelist.git
Project-URL: Issues, https://github.com/aarmn/pixelist/issues
Project-URL: Changelog, https://github.com/aarmn/pixelist/releases
Project-URL: Documentation, https://github.com/aarmn/pixelist#readme
Classifier: Development Status :: 4 - Beta
Classifier: Intended Audience :: Developers
Classifier: License :: OSI Approved :: MIT License
Classifier: Programming Language :: Python :: 3.8
Classifier: Programming Language :: Python :: 3.9
Classifier: Programming Language :: Python :: 3.10
Classifier: Programming Language :: Python :: 3.11
Classifier: Programming Language :: Python :: 3.12
Requires-Python: >=3.8
License-File: LICENSE
Requires-Dist: numpy>=2.2.1
Requires-Dist: pydantic>=2.10.5
Provides-Extra: display
Requires-Dist: matplotlib>=3.5.0; extra == "display"
Requires-Dist: opencv-python>=4.5.0; extra == "display"
Provides-Extra: test
Requires-Dist: pytest>=7.0.0; extra == "test"
Requires-Dist: pytest-cov>=4.0.0; extra == "test"
Requires-Dist: pytest-sugar>=0.9.7; extra == "test"
Requires-Dist: coverage[toml]>=7.3.2; extra == "test"
Requires-Dist: ruff>=0.1.9; extra == "test"
Provides-Extra: dev
Requires-Dist: build>=1.0.0; extra == "dev"
Requires-Dist: twine>=4.0.0; extra == "dev"
Requires-Dist: act-cli>=0.2.0; extra == "dev"
Requires-Dist: jupyterlab>=4.0.0; extra == "dev"
Provides-Extra: all
Requires-Dist: pixelist[dev,display,test]; extra == "all"
